startfile/__init__.py
startfile/utils.py
universal_startfile-0.4.dist-info/METADATA
universal_startfile-0.4.dist-info/WHEEL
universal_startfile-0.4.dist-info/licenses/LICENSE.md
universal_startfile-0.4.dist-info/RECORD
