Metadata-Version: 2.4
Name: universal-startfile
Version: 0.4
Summary: A cross-platform version of 'os.startfile' from the standard library.
License: MIT
License-File: LICENSE.md
Keywords: files,startfile,utilities
Author: Jace Browning
Author-email: jacebrowning@gmail.com
Requires-Python: >=3.9,<4.0
Classifier: Development Status :: 3 - Alpha
Classifier: Intended Audience :: Developers
Classifier: License :: OSI Approved :: MIT License
Classifier: Natural Language :: English
Classifier: Operating System :: OS Independent
Classifier: Programming Language :: Python
Classifier: Programming Language :: Python :: 3
Classifier: Programming Language :: Python :: 3.9
Classifier: Programming Language :: Python :: 3.10
Classifier: Programming Language :: Python :: 3.11
Classifier: Programming Language :: Python :: 3.12
Classifier: Programming Language :: Python :: 3.13
Classifier: Programming Language :: Python :: 3.14
Classifier: Topic :: Desktop Environment :: File Managers
Classifier: Topic :: Software Development :: Libraries
Classifier: Topic :: System :: Filesystems
Classifier: Topic :: Utilities
Project-URL: Documentation, https://universal-startfile.readthedocs.io
Project-URL: Homepage, https://pypi.org/project/universal-startfile
Project-URL: Repository, https://github.com/jacebrowning/universal-startfile
